alnoda_wrk/__init__.py
alnoda_wrk/alnoda_api.py
alnoda_wrk/builder.py
alnoda_wrk/cheatsheet.py
alnoda_wrk/conf_parser.py
alnoda_wrk/config_schema.py
alnoda_wrk/fileops.py
alnoda_wrk/globals.py
alnoda_wrk/install_app.py
alnoda_wrk/links.py
alnoda_wrk/main.py
alnoda_wrk/meta_about.py
alnoda_wrk/ports.py
alnoda_wrk/services.py
alnoda_wrk/share.py
alnoda_wrk/sign_in.py
alnoda_wrk/templates.py
alnoda_wrk/tui/__init__.py
alnoda_wrk/tui/admin.py
alnoda_wrk/tui/aliases_widget.py
alnoda_wrk/tui/appearance_widget.py
alnoda_wrk/tui/apps_services.py
alnoda_wrk/tui/cheatsheet_widget.py
alnoda_wrk/tui/description_widget.py
alnoda_wrk/tui/env_vars_widget.py
alnoda_wrk/tui/features_widget.py
alnoda_wrk/tui/gvars.py
alnoda_wrk/tui/helper_vidgets.py
alnoda_wrk/tui/home.py
alnoda_wrk/tui/interface_widget.py
alnoda_wrk/tui/links_widget.py
alnoda_wrk/tui/my_notes_widget.py
alnoda_wrk/tui/processes_widget.py
alnoda_wrk/tui/share_widget.py
alnoda_wrk/tui/signin_widget.py
alnoda_wrk/tui/zsh_widget.py
alnoda_wrk/ui_builder.py
alnoda_wrk/ui_styles.py
alnoda_wrk/upgrade.py
alnoda_wrk/versioning.py
alnoda_wrk/wrk/cheatsheet.json
alnoda_wrk/wrk/lineage.json
alnoda_wrk/wrk/links.json
alnoda_wrk/wrk/meta.json
alnoda_wrk/wrk/requires/deps.txt
alnoda_wrk/wrk/requires/mkdocs.txt
alnoda_wrk/wrk/ui/.gitignore
alnoda_wrk/wrk/ui/conf/ui-apps.json
alnoda_wrk/wrk/ui/docs/README.md
alnoda_wrk/wrk/ui/docs/about.md
alnoda_wrk/wrk/ui/docs/assets/favicon.ico
alnoda_wrk/wrk/ui/docs/assets/home/terminal.png
alnoda_wrk/wrk/ui/docs/assets/laptop-circle-white.svg
alnoda_wrk/wrk/ui/docs/assets/laptop-circle.svg
alnoda_wrk/wrk/ui/docs/cheatsheet.md
alnoda_wrk/wrk/ui/docs/javascript/config.js
alnoda_wrk/wrk/ui/docs/manifest.txt
alnoda_wrk/wrk/ui/docs/pages/admin/admin.png
alnoda_wrk/wrk/ui/docs/pages/admin/terminal.png
alnoda_wrk/wrk/ui/docs/pages/admin.md
alnoda_wrk/wrk/ui/docs/pages/my_apps/port-8026.png
alnoda_wrk/wrk/ui/docs/pages/my_apps/port-8027.png
alnoda_wrk/wrk/ui/docs/pages/my_apps/port-8028.png
alnoda_wrk-0.4.33.dist-info/entry_points.txt
alnoda_wrk-0.4.33.dist-info/LICENSE
alnoda_wrk-0.4.33.dist-info/WHEEL
alnoda_wrk-0.4.33.dist-info/METADATA
alnoda_wrk-0.4.33.dist-info/RECORD
