Metadata-Version: 2.1
Name: alnoda-wrk
Version: 0.4.33
Summary: A tool to build Alnoda workspaces
License: AGPL-3.0
Author: bluxmit
Author-email: bluxmit@gmail.com
Requires-Python: >=3.8,<4.0
Classifier: License :: OSI Approved :: GNU Affero General Public License v3
Classifier: Programming Language :: Python :: 3
Classifier: Programming Language :: Python :: 3.10
Classifier: Programming Language :: Python :: 3.8
Classifier: Programming Language :: Python :: 3.9
Requires-Dist: Cerberus (>=1.3,<2.0)
Requires-Dist: PyYAML (>=6.0,<7.0)
Requires-Dist: jinja2 (>=3.0,<4.0)
Requires-Dist: packaging (==23.0)
Requires-Dist: pyTermTk (>=0.10.22a0,<0.11.0)
Requires-Dist: pyfiglet (>=0.8.post1,<0.9)
Requires-Dist: requests (>=2.28.2,<3.0.0)
Requires-Dist: typer[all] (>=0.6,<0.7)
